pytorch_utils/__init__.py
pytorch_utils/data_modules.py
pytorch_utils/dataset_configurations.py
pytorch_utils/datasets.py
pytorch_utils/exceptions.py
pytorch_utils/logging/loggers.py
pytorch_utils/logging/utils.py
pytorch_utils/metrics.py
pytorch_utils/miscellaneous.py
pytorch_utils/modules.py
pytorch_utils/pandas/data_formatting.py
pytorch_utils/pandas/utils.py
pytorch_utils/utils.py
ai_helpers_pytorch_utils-0.1.0a1.dist-info/METADATA
ai_helpers_pytorch_utils-0.1.0a1.dist-info/WHEEL
ai_helpers_pytorch_utils-0.1.0a1.dist-info/RECORD
