Metadata-Version: 2.1
Name: ai-helpers-pytorch-utils
Version: 0.1.0a1
Summary: Common PyTorch utils
Home-page: https://github.com/ai-helpers/pytorch-utils
Keywords: machine-learning,pytorch,utils
Author: Corentin Vasseur
Author-email: vasseur.corentin@gmail.com
Requires-Python: >=3.10,<3.11
Classifier: Programming Language :: Python :: 3
Classifier: Programming Language :: Python :: 3.10
Classifier: Topic :: Software Development :: Libraries :: Python Modules
Requires-Dist: mlflow (>=2.13.0,<3.0.0)
Requires-Dist: numpy (==1.26.4)
Requires-Dist: pandas (==2.0.3)
Requires-Dist: plotly (>=5.14.1,<6.0.0)
Requires-Dist: pytorch-lightning (>=2.1.3,<3.0.0)
Requires-Dist: scikit-learn (==1.3.2)
Requires-Dist: torch (==2.2.2)
Requires-Dist: torchinfo (>=1.8.0,<2.0.0)
Project-URL: Documentation, https://ai-helpers.github.io/pytorch-utils/
Project-URL: Repository, https://github.com/ai-helpers/pytorch-utils
